benchmark/__init__.py
benchmark/scripts/__init__.py
benchmark/scripts/benchmark_resnet.py
benchmark/scripts/data_generator.py
benchmark/scripts/logging_metrics.py
benchmark/scripts/run_benchmark.py
benchmark/scripts/models/__init__.py
benchmark/scripts/models/dataset_utils.py
benchmark/scripts/models/lstm_synthetic.py
benchmark/scripts/models/lstm_text_generation.py
benchmark/scripts/models/model_config.py
benchmark/scripts/models/resnet.py
benchmark/scripts/models/resnet50_benchmark.py
benchmark/scripts/models/resnet50_benchmark_tf_keras.py
benchmark/scripts/models/timehistory.py
docs/__init__.py
docs/autogen.py
keras/__init__.py
keras/activations.py
keras/callbacks.py
keras/constraints.py
keras/initializers.py
keras/losses.py
keras/metrics.py
keras/models.py
keras/objectives.py
keras/optimizers.py
keras/regularizers.py
keras/applications/__init__.py
keras/applications/densenet.py
keras/applications/imagenet_utils.py
keras/applications/inception_resnet_v2.py
keras/applications/inception_v3.py
keras/applications/mobilenet.py
keras/applications/mobilenet_v2.py
keras/applications/mobilenetv2.py
keras/applications/nasnet.py
keras/applications/resnet50.py
keras/applications/vgg16.py
keras/applications/vgg19.py
keras/applications/xception.py
keras/backend/__init__.py
keras/backend/cntk_backend.py
keras/backend/common.py
keras/backend/mxnet_backend.py
keras/backend/tensorflow_backend.py
keras/backend/theano_backend.py
keras/datasets/__init__.py
keras/datasets/boston_housing.py
keras/datasets/cifar.py
keras/datasets/cifar10.py
keras/datasets/cifar100.py
keras/datasets/fashion_mnist.py
keras/datasets/imdb.py
keras/datasets/mnist.py
keras/datasets/reuters.py
keras/engine/__init__.py
keras/engine/base_layer.py
keras/engine/input_layer.py
keras/engine/network.py
keras/engine/saving.py
keras/engine/sequential.py
keras/engine/topology.py
keras/engine/training.py
keras/engine/training_arrays.py
keras/engine/training_generator.py
keras/engine/training_utils.py
keras_mxnet-2.2.4.2.dist-info/LICENSE
keras_mxnet-2.2.4.2.dist-info/METADATA
keras_mxnet-2.2.4.2.dist-info/WHEEL
keras_mxnet-2.2.4.2.dist-info/top_level.txt
keras_mxnet-2.2.4.2.dist-info/RECORD
