Metadata-Version: 2.1
Name: keras-mxnet
Version: 2.2.4.2
Summary: Deep Learning for humans. Keras with highly scalable,                   high performance Apache MXNet backend support.
Home-page: https://github.com/awslabs/keras-apache-mxnet
Author: Amazon Web Services
License: MIT
Platform: UNKNOWN
Classifier: Development Status :: 5 - Production/Stable
Classifier: Intended Audience :: Developers
Classifier: Intended Audience :: Education
Classifier: Intended Audience :: Science/Research
Classifier: License :: OSI Approved :: MIT License
Classifier: Programming Language :: Python :: 2
Classifier: Programming Language :: Python :: 2.7
Classifier: Programming Language :: Python :: 3
Classifier: Programming Language :: Python :: 3.6
Classifier: Topic :: Software Development :: Libraries
Classifier: Topic :: Software Development :: Libraries :: Python Modules
Requires-Dist: numpy (>=1.9.1)
Requires-Dist: scipy (>=0.14)
Requires-Dist: six (>=1.9.0)
Requires-Dist: pyyaml
Requires-Dist: h5py
Requires-Dist: keras-applications (>=1.0.6)
Requires-Dist: keras-preprocessing (>=1.0.5)
Provides-Extra: tests
Requires-Dist: pytest ; extra == 'tests'
Requires-Dist: pytest-pep8 ; extra == 'tests'
Requires-Dist: pytest-xdist ; extra == 'tests'
Requires-Dist: pytest-cov ; extra == 'tests'
Requires-Dist: pytest-timeout ; extra == 'tests'
Requires-Dist: pandas ; extra == 'tests'
Requires-Dist: requests ; extra == 'tests'
Provides-Extra: visualize
Requires-Dist: pydot (>=1.2.4) ; extra == 'visualize'
